pycythonizer/__init__.py
pycythonizer/cignore.py
pycythonizer/cli.py
pycythonizer/compiler.py
pycythonizer/log.py
pycythonizer-0.0.7.dist-info/licenses/LICENSE
pycythonizer-0.0.7.dist-info/METADATA
pycythonizer-0.0.7.dist-info/WHEEL
pycythonizer-0.0.7.dist-info/entry_points.txt
pycythonizer-0.0.7.dist-info/top_level.txt
pycythonizer-0.0.7.dist-info/RECORD
